vcelerytaskrunner/__init__.py
vcelerytaskrunner/admin.py
vcelerytaskrunner/apps.py
vcelerytaskrunner/models.py
vcelerytaskrunner/views.py
vcelerytaskrunner/migrations/0001_initial.py
vcelerytaskrunner/migrations/__init__.py
vcelerytaskrunner/services/__init__.py
vcelerytaskrunner/services/task_registry.py
vcelerytaskrunner/services/task_runner.py
vcelerytaskrunner/static/app/tasks.css
vcelerytaskrunner/templates/vcelerytaskrunner/layout.html
vcelerytaskrunner/templates/vcelerytaskrunner/task_run.html
vcelerytaskrunner/templates/vcelerytaskrunner/task_run_result.html
vcelerytaskrunner/templates/vcelerytaskrunner/tasks.html
vcelerytaskrunner/tests/__init__.py
vcelerytaskrunner/tests/views/__init__.py
vcelerytaskrunner/tests/views/test_task_runs.py
vcelery_task_runner-1.1.0.dist-info/LICENSE
vcelery_task_runner-1.1.0.dist-info/METADATA
vcelery_task_runner-1.1.0.dist-info/WHEEL
vcelery_task_runner-1.1.0.dist-info/top_level.txt
vcelery_task_runner-1.1.0.dist-info/RECORD
