Metadata-Version: 2.1
Name: vcelery-task-runner
Version: 1.1.0
Summary: UI to allow interactively starting Celery tasks
Author-email: Van Ly <vancly@hotmail.com>
License: MIT License
Project-URL: Homepage, https://github.com/bluedenim/vcelery-task-runner
Keywords: celery,python,django
Classifier: License :: OSI Approved :: MIT License
Classifier: Programming Language :: Python
Classifier: Programming Language :: Python :: 3
Requires-Python: >=3.8
License-File: LICENSE
Requires-Dist: django>=4.2.16
Requires-Dist: celery>=5.3.6
Requires-Dist: djangorestframework>=3.15.2
Requires-Dist: pydantic>=2.10.1
Provides-Extra: dev
Requires-Dist: build; extra == "dev"
Requires-Dist: twine; extra == "dev"
